[
  {
    "fileName": "Margherita",
    "url": "https://www.dominos.co.in/files/items/Margherit.jpg"
  },
  {
    "fileName": "Double Cheese Margherita",
    "url": "https://www.dominos.co.in/files/items/Double_Cheese_Margherita.jpg"
  },
  {
    "fileName": "Farm House",
    "url": "https://www.dominos.co.in/files/items/Farmhouse.jpg"
  },
  {
    "fileName": "Peppy Paneer",
    "url": "https://www.dominos.co.in/files/items/Peppy_Paneer.jpg"
  },
  {
    "fileName": "Mexican Green Wave",
    "url": "https://www.dominos.co.in/files/items/Mexican_Green_Wave.jpg"
  },
  {
    "fileName": "Deluxe Veggie",
    "url": "https://www.dominos.co.in/files/items/Deluxe_Veggie.jpg"
  },
  {
    "fileName": "Veg Extravaganza",
    "url": "https://www.dominos.co.in/files/items/Veg_Extravaganz.jpg"
  },
  {
    "fileName": "Cheese N Corn",
    "url": "https://www.dominos.co.in/files/items/Corn_&_Cheese.jpg"
  },
  {
    "fileName": "Paneer Makhani",
    "url": "https://www.dominos.co.in/files/items/Paneer_Makhni.jpg"
  },
  {
    "fileName": "Veggie Paradise",
    "url": "https://www.dominos.co.in/files/items/Digital_Veggie_Paradise_olo_266x265.jpg"
  },
  {
    "fileName": "Fresh Veggie",
    "url": "https://www.dominos.co.in/files/items/Fresh_Veggie.jpg"
  },
  {
    "fileName": "Indi Tandoori Paneer",
    "url": "https://www.dominos.co.in/files/items/IndianTandooriPaneer.jpg"
  },
  {
    "fileName": "Pepper Barbecue Chicken",
    "url": "https://www.dominos.co.in/files/items/Pepper_Barbeque.jpg"
  },
  {
    "fileName": "Chicken Sausage",
    "url": "https://www.dominos.co.in/files/items/Chicken_Sausage.jpg"
  },
  {
    "fileName": "Chicken Golden Delight",
    "url": "https://www.dominos.co.in/files/items/Chicken_Golden_Delight.jpg"
  },
  {
    "fileName": "Non Veg Supreme",
    "url": "https://www.dominos.co.in/files/items/Non-Veg_Supreme.jpg"
  },
  {
    "fileName": "Chicken Dominator",
    "url": "https://www.dominos.co.in/files/items/Dominator.jpg"
  },
  {
    "fileName": "Pepper Barbecue & Onion",
    "url": "https://www.dominos.co.in/files/items/Pepper_Barbeque_&_Onion.jpg"
  },
  {
    "fileName": "Chicken Fiesta",
    "url": "https://www.dominos.co.in/files/items/chunky-chicken.png"
  },
  {
    "fileName": "Indi Chicken Tikka",
    "url": "https://www.dominos.co.in/files/items/IndianChickenTikka.jpg"
  }
]